{"expireTime":9007200816804222000,"key":"transformer-remark-markdown-html-ast-5325964632407348b77523b17a430092-gatsby-remark-images-","val":{"type":"root","children":[{"type":"element","tagName":"p","properties":{},"children":[{"type":"text","value":"Auf der 30. Delegiertenversammlung in Berlin beschäftigten wir uns thematisch mit dem Klimawandel. Vor allem die existenzielle Bedrohung kleiner Inseln durch Überflutung waren dabei ein Thema.","position":{"start":{"line":2,"column":1,"offset":1},"end":{"line":2,"column":193,"offset":193}}}],"position":{"start":{"line":2,"column":1,"offset":1},"end":{"line":2,"column":193,"offset":193}}},{"type":"text","value":"\n"},{"type":"element","tagName":"p","properties":{},"children":[{"type":"text","value":"Darüber hinaus verbrachten wir die Zeit in Berlin mit der ","position":{"start":{"line":4,"column":1,"offset":195},"end":{"line":4,"column":59,"offset":253}}}],"position":{"start":{"line":4,"column":1,"offset":195},"end":{"line":4,"column":59,"offset":253}}}],"position":{"start":{"line":1,"column":1,"offset":0},"end":{"line":5,"column":1,"offset":254}}}}